omnyx/__init__.py
omnyx/data/__init__.py
omnyx/data/baseclass.py
omnyx/data/dataclass.py
omnyx/data/parser_annotation.py
omnyx/data/parser_clip.py
omnyx/data/parser_detection.py
omnyx/data/rules.py
omnyx/data/type_annotation.py
omnyx/data/type_obstacle.py
omnyx/data/type_sensor.py
omnyx/data/utils.py
omnyx/fileio/__init__.py
omnyx/fileio/read_file.py
omnyx/fileio/write_file.py
omnyx/math/__init__.py
omnyx/math/box.py
omnyx/math/colormap.py
omnyx/math/geometry.py
omnyx/math/iou.py
omnyx/math/matcher.py
omnyx/math/numeric.py
omnyx/sensor/__init__.py
omnyx/sensor/camera.py
omnyx/sensor/lidar.py
omnyx/sensor/pose.py
omnyx/system/__init__.py
omnyx/system/environ.py
omnyx/system/logging.py
omnyx/system/threading.py
omnyx/system/time.py
omnyx/vis/__init__.py
omnyx/vis/interface.py
omnyx/vis/render.py
omnyx/vis/viewer_bev.py
omnyx/vis/viewer_o3d.py
omnyx-0.0.2.dist-info/LICENSE
omnyx-0.0.2.dist-info/METADATA
omnyx-0.0.2.dist-info/WHEEL
omnyx-0.0.2.dist-info/top_level.txt
omnyx-0.0.2.dist-info/RECORD
