Metadata-Version: 2.1
Name: omnyx
Version: 0.0.2
Summary: UNKNOWN
Home-page: https://github.com/bochent/omnyx/
Author: tongbochen
Author-email: bochen.tong@outlook.com
License: MIT Licence
Platform: UNKNOWN
License-File: LICENSE
Requires-Dist: av
Requires-Dist: colorlog
Requires-Dist: numba
Requires-Dist: numpy
Requires-Dist: open3d
